Metadata-Version: 1.1
Name: ypinyin
Version: 0.5.6
Summary: translate chinese hanzi to pinyin by python
Home-page: https://github.com/liuguangyuan0532/ypinyin
Author: Eric Lo
Author-email: liuguangyuan0532@gmail.com
License: BSD
Keywords: pinyin
Platform: UNKNOWN
Classifier: Intended Audience :: Developers
Classifier: License :: OSI Approved :: BSD License
Classifier: Operating System :: OS Independent
Classifier: Programming Language :: Python :: 2
Classifier: Programming Language :: Python :: 2.6
Classifier: Programming Language :: Python :: 2.7
Classifier: Programming Language :: Python :: 3
Classifier: Programming Language :: Python :: 3.3
Classifier: Programming Language :: Python :: 3.4
Classifier: Programming Language :: Python :: 3.5
Classifier: Topic :: Software Development :: Libraries :: Python Modules
